cmdsurf/__init__.py
cmdsurf/__main__.py
cmdsurf-0.1.4.dist-info/licenses/LICENSE
cmdsurf-0.1.4.dist-info/METADATA
cmdsurf-0.1.4.dist-info/WHEEL
cmdsurf-0.1.4.dist-info/entry_points.txt
cmdsurf-0.1.4.dist-info/top_level.txt
cmdsurf-0.1.4.dist-info/RECORD
